ml_contracts/__init__.py
ml_contracts/contracts.py
ml_contracts/exceptions.py
ml_contracts/features.py
ml_contracts-0.1.0.dist-info/METADATA
ml_contracts-0.1.0.dist-info/WHEEL
ml_contracts-0.1.0.dist-info/licenses/LICENSE
ml_contracts-0.1.0.dist-info/RECORD
